protmaster/__init__.py
protmaster/protmaster.py
protmaster-0.0.3.dist-info/METADATA
protmaster-0.0.3.dist-info/WHEEL
protmaster-0.0.3.dist-info/top_level.txt
protmaster-0.0.3.dist-info/RECORD
