Metadata-Version: 2.1
Name: protmaster
Version: 0.0.3
Summary: A powerful proteomic analysis tool
Home-page: UNKNOWN
Author: Tang Ting
Author-email: ttang1900@gmail.com
License: UNKNOWN
Platform: UNKNOWN
Classifier: Programming Language :: Python :: 3
Classifier: License :: OSI Approved :: MIT License
Classifier: Operating System :: OS Independent
Requires-Python: >=3.6
Requires-Dist: numpy (>=1.19.2)
Requires-Dist: pandas (>=1.3.3)
Requires-Dist: matplotlib (>=3.3.2)
Requires-Dist: pymzml (>=2.4.7)
Requires-Dist: scipy (>=1.6.2)
Requires-Dist: molmass (==2021.6.18)
Requires-Dist: tqdm (>=4.62.3)
Requires-Dist: openpyxl (>=3.0.9)
Requires-Dist: networkx (>=2.6.3)
Requires-Dist: scikit-learn (>=1.0.2)
Requires-Dist: requests
Requires-Dist: beautifulsoup4
